musicnn_keras/__init__.py
musicnn_keras/configuration.py
musicnn_keras/extractor.py
musicnn_keras/tagger.py
musicnn_keras-0.1.0.dist-info/LICENSE.md
musicnn_keras-0.1.0.dist-info/METADATA
musicnn_keras-0.1.0.dist-info/WHEEL
musicnn_keras-0.1.0.dist-info/top_level.txt
musicnn_keras-0.1.0.dist-info/RECORD
