Metadata-Version: 2.1
Name: musicnn-keras
Version: 0.1.0
Summary: Pronounced as "musician", musicnn is a set of pre-trained deep convolutional neural networks for music audio tagging. Musicnn_keras is a tf.keras implementation of musicnn
Home-page: https://github.com/Quint-e/musicnn_keras
Author: Elio Quinton
License: ISC
Keywords: audio music deep learning tagging tensorflow keras machine listening
Platform: UNKNOWN
Classifier: License :: OSI Approved :: ISC License (ISCL)
Classifier: Programming Language :: Python
Classifier: Development Status :: 3 - Alpha
Classifier: Intended Audience :: Developers
Classifier: Intended Audience :: Science/Research
Classifier: Topic :: Multimedia :: Sound/Audio :: Analysis
Classifier: Programming Language :: Python :: 3
Classifier: Programming Language :: Python :: 3.7
Requires-Dist: librosa (>=0.7.0)
Requires-Dist: tensorflow (>=2.0)
Requires-Dist: numpy (<1.17,>=1.14.5)
